[
    {
        "id": "P01",
        "name": "Pantalon01",
        "description": "Pantal贸n jogging negro",
        "price": 2560,
        "image": "img/ropa/P01.jpg",
        "isPopular": true
    },
    {
        "id": "P02",
        "name": "Pantalon02",
        "description": "Pantal贸n jogging estilo camuflado negro y gris",
        "price": 2690,
        "image": "img/ropa/P02.jpg",
        "isPopular": false
    },
    {
        "id": "P03",
        "name": "Pantalon03",
        "description": "Pantalon jogging suelto gris",
        "price": 2000,
        "image": "img/ropa/P03.jpg",
        "isPopular": false
    },
    {
        "id": "P04",
        "name": "Pantalon04",
        "description": "Pantal贸n gabardina negro",
        "price": 3290,
        "image": "img/ropa/P04.jpg",
        "isPopular": true
    },
    {
        "id": "P05",
        "name": "Pantalon05",
        "description": "Pantal贸n jogging suelto negro",
        "price": 2660,
        "image": "img/ropa/P05.jpg",
        "isPopular": false
    }
]